soluble_master/conf.py
soluble_master/soluble/master.py
soluble_minion/conf.py
soluble_minion/soluble/minion.py
soluble-3.0.0.dist-info/METADATA
soluble-3.0.0.dist-info/WHEEL
soluble-3.0.0.dist-info/entry_points.txt
soluble-3.0.0.dist-info/RECORD
