Metadata-Version: 2.3
Name: soluble
Version: 3.0.0
Summary: Set up a dissolvable, ephemeral salt minion using salt-ssh
Author-email: Tyler Levy Conde <tyler.levy-conde@broadcomm.com>
Classifier: Development Status :: 5 - Production/Stable
Classifier: Environment :: Console
Classifier: Intended Audience :: Developers
Classifier: Intended Audience :: Information Technology
Classifier: Intended Audience :: System Administrators
Classifier: License :: OSI Approved :: Apache Software License
Classifier: Operating System :: OS Independent
Classifier: Programming Language :: Python
Classifier: Programming Language :: Python :: 3.10
Classifier: Programming Language :: Python :: 3.11
Classifier: Programming Language :: Python :: 3.12
Requires-Python: >=3.10
Requires-Dist: distro
Requires-Dist: importlib-metadata<5.0
Requires-Dist: pop>=27.1.0
Requires-Dist: salt-ssh
Provides-Extra: test
Requires-Dist: asynctest; extra == 'test'
Requires-Dist: mock; extra == 'test'
Requires-Dist: pytest-asyncio; extra == 'test'
Requires-Dist: pytest-pop>=8.0; extra == 'test'
Requires-Dist: pytest>=6.2.5; extra == 'test'
